rewe_ebon_parser/__init__.py
rewe_ebon_parser/classes.py
rewe_ebon_parser/cli.py
rewe_ebon_parser/output.py
rewe_ebon_parser/parse.py
rewe_ebon_parser/table.py
rewe_ebon_parser-0.0.7.dist-info/METADATA
rewe_ebon_parser-0.0.7.dist-info/WHEEL
rewe_ebon_parser-0.0.7.dist-info/entry_points.txt
rewe_ebon_parser-0.0.7.dist-info/licenses/LICENSE
rewe_ebon_parser-0.0.7.dist-info/RECORD
