Metadata-Version: 2.4
Name: rewe-ebon-parser
Version: 0.0.7
Summary: Parse and convert REWE eBons (digital receipts) to JSON and CSV.
Project-URL: homepage, https://github.com/e-kotov/rewe-ebon-parser
Project-URL: source, https://github.com/e-kotov/rewe-ebon-parser
Project-URL: issues, https://github.com/e-kotov/rewe-ebon-parser/issues
Project-URL: changelog, https://github.com/e-kotov/rewe-ebon-parser/blob/main/CHANGELOG.md
Author-email: Egor Kotov <kotov.egor@gmail.com>
License-File: LICENSE
Classifier: License :: OSI Approved :: MIT License
Classifier: Operating System :: OS Independent
Classifier: Programming Language :: Python :: 3
Requires-Python: >=3.6
Requires-Dist: pdfplumber
Requires-Dist: pytest>=7.0.1
Requires-Dist: pytz
Requires-Dist: tqdm
Provides-Extra: dev
Requires-Dist: pytest; extra == 'dev'
Requires-Dist: pytest-asyncio; extra == 'dev'
Provides-Extra: docs
Requires-Dist: myst-parser; extra == 'docs'
Requires-Dist: recommonmark; extra == 'docs'
Requires-Dist: sphinx; extra == 'docs'
Requires-Dist: sphinx-autodoc-typehints; extra == 'docs'
Requires-Dist: sphinx-rtd-theme; extra == 'docs'
